mongo_test_ts/__init__.py
mongo_test_ts/mongo_crud.py
mongo_test_ts-0.2.1.dist-info/METADATA
mongo_test_ts-0.2.1.dist-info/WHEEL
mongo_test_ts-0.2.1.dist-info/top_level.txt
mongo_test_ts-0.2.1.dist-info/RECORD
